odoo/addons/sale_order_revision/README.rst
odoo/addons/sale_order_revision/__init__.py
odoo/addons/sale_order_revision/__manifest__.py
odoo/addons/sale_order_revision/i18n/es.po
odoo/addons/sale_order_revision/i18n/it.po
odoo/addons/sale_order_revision/i18n/pt.po
odoo/addons/sale_order_revision/i18n/pt_BR.po
odoo/addons/sale_order_revision/i18n/sale_order_revision.pot
odoo/addons/sale_order_revision/models/__init__.py
odoo/addons/sale_order_revision/models/sale_order.py
odoo/addons/sale_order_revision/readme/CONTRIBUTORS.md
odoo/addons/sale_order_revision/readme/DESCRIPTION.md
odoo/addons/sale_order_revision/readme/INSTALL.md
odoo/addons/sale_order_revision/static/description/icon.png
odoo/addons/sale_order_revision/static/description/index.html
odoo/addons/sale_order_revision/tests/__init__.py
odoo/addons/sale_order_revision/tests/test_sale_order_revision.py
odoo/addons/sale_order_revision/view/sale_order.xml
odoo_addon_sale_order_revision-18.0.1.0.0.6.dist-info/METADATA
odoo_addon_sale_order_revision-18.0.1.0.0.6.dist-info/WHEEL
odoo_addon_sale_order_revision-18.0.1.0.0.6.dist-info/top_level.txt
odoo_addon_sale_order_revision-18.0.1.0.0.6.dist-info/RECORD
