Metadata-Version: 2.1
Name: odoo-addon-sale_order_revision
Version: 18.0.1.0.0.6
Requires-Python: >=3.10
Requires-Dist: odoo-addon-base_revision==18.0.*
Requires-Dist: odoo==18.0.*
Summary: Keep track of revised quotations
Home-page: https://github.com/OCA/sale-workflow
License: AGPL-3
Author: Agile Business Group,Dreambits,Camptocamp,Akretion,Serpent Consulting Services Pvt. Ltd.,Ecosoft,Odoo Community Association (OCA)
Author-email: support@odoo-community.org
Classifier: Programming Language :: Python
Classifier: Framework :: Odoo
Classifier: Framework :: Odoo :: 18.0
Classifier: License :: OSI Approved :: GNU Affero General Public License v3
